LICENSE
README.md
setup.cfg
setup.py
tests/test_build.py
tiktok_dlpy.egg-info/PKG-INFO
tiktok_dlpy.egg-info/SOURCES.txt
tiktok_dlpy.egg-info/dependency_links.txt
tiktok_dlpy.egg-info/requires.txt
tiktok_dlpy.egg-info/top_level.txt
tiktokdl/__init__.py
tiktokdl/captcha.py
tiktokdl/download_post.py
tiktokdl/exceptions.py
tiktokdl/image_processing.py
tiktokdl/post_data.py
tiktokdl/session_store.py
tiktokdl/tiktok_magic.py