Metadata-Version: 2.1
Name: tiktok-dlpy
Version: 2.2.0
Summary: A package to download TikTok videos or slideshows by URL without needing to login
Home-page: https://github.com/Fluxticks/TikTokDL
Download-URL: https://github.com/Fluxticks/TikTokDL/archive/v2.2.0.tar.gz
Author: Fluxticks
Keywords: tiktok,playwright,async
Classifier: Development Status :: 5 - Production/Stable
Classifier: Intended Audience :: Developers
Classifier: License :: OSI Approved :: GNU General Public License v3 (GPLv3)
Classifier: Programming Language :: Python :: 3.8
Classifier: Programming Language :: Python :: 3.9
Classifier: Programming Language :: Python :: 3.10
License-File: LICENSE
Requires-Dist: playwright
Requires-Dist: requests
